langtools/__init__.py
langtools/mortgage.py
langtools/pornhub.py
langtools/visa.py
langtools/web_browser.py
langtools-0.3.0.dist-info/LICENSE
langtools-0.3.0.dist-info/METADATA
langtools-0.3.0.dist-info/WHEEL
langtools-0.3.0.dist-info/RECORD
