Metadata-Version: 2.1
Name: langtools
Version: 0.3.0
Summary: 
Author: なるみ
Author-email: toucans-cutouts0f@icloud.com
Requires-Python: >=3.9,<3.12
Classifier: Programming Language :: Python :: 3
Classifier: Programming Language :: Python :: 3.9
Classifier: Programming Language :: Python :: 3.10
Classifier: Programming Language :: Python :: 3.11
Requires-Dist: beautifulsoup4 (>=4.12.2,<5.0.0)
Requires-Dist: cloudscraper (>=1.2.71,<2.0.0)
Requires-Dist: langchain (>=0.0.209,<0.0.210)
Requires-Dist: mortgage (>=1.0.5,<2.0.0)
Requires-Dist: openai (>=0.27.8,<0.28.0)
Requires-Dist: pornhub-api (>=0.3.0,<0.4.0)
Requires-Dist: python-dotenv (>=1.0.0,<2.0.0)
Requires-Dist: retry (>=0.9.2,<0.10.0)
